{
  "$schema": "../schemas/technology.json",
  "name": "Electron",
  "normalizedName": "electron",
  "platforms": {
    "Windows": "✅",
    "macOS": "✅",
    "Linux": "✅",
    "Android": "",
    "iOS": ""
  },
  "languages": {
    "C++": "✅",
    "C#": "",
    "Go": "",
    "Java": "",
    "JavaScript": "✅",
    "Rust": ""
  },
  "rendering": {
    "Browser engine": "✅",
    "Platform controls": "",
    "Direct drawing": ""
  },
  "releases": [
    {
      "version": "v21.3.1",
      "date": "2022-11-23T18:40:32Z"
    },
    {
      "version": "v21.3.0",
      "date": "2022-11-17T00:08:53Z"
    },
    {
      "version": "v21.2.3",
      "date": "2022-11-09T19:47:03Z"
    },
    {
      "version": "v21.2.2",
      "date": "2022-11-02T19:20:51Z"
    },
    {
      "version": "v21.2.1",
      "date": "2022-10-31T22:30:51Z"
    },
    {
      "version": "v21.2.0",
      "date": "2022-10-19T18:20:03Z"
    },
    {
      "version": "v21.1.1",
      "date": "2022-10-12T19:41:48Z"
    },
    {
      "version": "v21.1.0",
      "date": "2022-10-05T19:28:41Z"
    },
    {
      "version": "v21.0.1",
      "date": "2022-09-28T18:49:51Z"
    },
    {
      "version": "v21.0.0",
      "date": "2022-09-26T21:35:45Z"
    },
    {
      "version": "v20.3.7",
      "date": "2022-11-23T18:23:19Z"
    },
    {
      "version": "v20.3.6",
      "date": "2022-11-21T20:50:48Z"
    },
    {
      "version": "v20.3.5",
      "date": "2022-11-09T19:16:33Z"
    },
    {
      "version": "v20.3.4",
      "date": "2022-11-02T19:20:52Z"
    },
    {
      "version": "v20.3.3",
      "date": "2022-10-19T18:24:01Z"
    },
    {
      "version": "v20.3.2",
      "date": "2022-10-12T19:39:42Z"
    },
    {
      "version": "v20.3.1",
      "date": "2022-10-05T19:09:20Z"
    },
    {
      "version": "v20.3.0",
      "date": "2022-09-28T18:46:27Z"
    },
    {
      "version": "v20.2.0",
      "date": "2022-09-22T00:04:09Z"
    },
    {
      "version": "v20.1.4",
      "date": "2022-09-14T18:44:45Z"
    },
    {
      "version": "v20.1.3",
      "date": "2022-09-08T22:05:03Z"
    },
    {
      "version": "v20.1.2",
      "date": "2022-09-07T19:47:05Z"
    },
    {
      "version": "v20.1.1",
      "date": "2022-08-31T19:00:40Z"
    },
    {
      "version": "v20.1.0",
      "date": "2022-08-24T19:07:31Z"
    },
    {
      "version": "v20.0.3",
      "date": "2022-08-17T18:59:23Z"
    },
    {
      "version": "v20.0.2",
      "date": "2022-08-10T21:00:50Z"
    },
    {
      "version": "v20.0.1",
      "date": "2022-08-03T18:33:24Z"
    },
    {
      "version": "v20.0.0",
      "date": "2022-08-01T22:19:41Z"
    },
    {
      "version": "v19.1.8",
      "date": "2022-11-28T20:57:25Z"
    },
    {
      "version": "v19.1.7",
      "date": "2022-11-23T18:34:03Z"
    },
    {
      "version": "v19.1.6",
      "date": "2022-11-16T21:36:37Z"
    },
    {
      "version": "v19.1.5",
      "date": "2022-11-09T20:06:29Z"
    },
    {
      "version": "v19.1.4",
      "date": "2022-11-02T19:15:59Z"
    },
    {
      "version": "v19.1.3",
      "date": "2022-10-12T19:32:11Z"
    },
    {
      "version": "v19.1.2",
      "date": "2022-10-05T19:01:47Z"
    },
    {
      "version": "v19.1.1",
      "date": "2022-09-28T18:41:24Z"
    },
    {
      "version": "v19.1.0",
      "date": "2022-09-23T22:31:10Z"
    },
    {
      "version": "v19.0.17",
      "date": "2022-09-14T18:46:57Z"
    },
    {
      "version": "v19.0.16",
      "date": "2022-09-08T00:18:53Z"
    },
    {
      "version": "v19.0.15",
      "date": "2022-08-31T19:06:33Z"
    },
    {
      "version": "v19.0.14",
      "date": "2022-08-24T19:38:03Z"
    },
    {
      "version": "v19.0.13",
      "date": "2022-08-17T18:45:21Z"
    },
    {
      "version": "v19.0.12",
      "date": "2022-08-10T18:50:25Z"
    },
    {
      "version": "v19.0.11",
      "date": "2022-08-03T18:27:22Z"
    },
    {
      "version": "v19.0.10",
      "date": "2022-07-27T20:08:01Z"
    },
    {
      "version": "v19.0.9",
      "date": "2022-07-21T22:14:37Z"
    },
    {
      "version": "v19.0.8",
      "date": "2022-07-06T19:23:51Z"
    },
    {
      "version": "v19.0.7",
      "date": "2022-06-30T19:59:16Z"
    },
    {
      "version": "v19.0.6",
      "date": "2022-06-22T18:54:13Z"
    },
    {
      "version": "v19.0.5",
      "date": "2022-06-20T19:44:30Z"
    },
    {
      "version": "v19.0.4",
      "date": "2022-06-08T18:27:02Z"
    },
    {
      "version": "v19.0.3",
      "date": "2022-06-03T05:14:51Z"
    },
    {
      "version": "v19.0.2",
      "date": "2022-06-01T18:57:08Z"
    },
    {
      "version": "v19.0.1",
      "date": "2022-05-25T19:16:40Z"
    },
    {
      "version": "v19.0.0",
      "date": "2022-05-23T21:15:17Z"
    }
  ],
  "codeLicense": {
    "name": "MIT",
    "url": "https://github.com/electron/electron/blob/6fdf350bea8ec5452b66043cd81eff6917802068/LICENSE"
  },
  "url": "https://www.electronjs.org",
  "community": "https://discord.com/invite/electron",
  "documentation": "https://www.electronjs.org/docs/latest/"
}